{
  "BTC": {
    "price": 76090.01,
    "change": 0.45
  },
  "ETH": {
    "price": 2261.46,
    "change": 0.4
  },
  "GOLD": {
    "price": 4611.9,
    "change": 1.1
  },
  "SILVER": {
    "price": 73.59,
    "change": 2.08
  },
  "OIL": {
    "price": 108.19,
    "change": 1.23
  },
  "S&P 500": {
    "price": 7135.95,
    "change": -0.04
  },
  "DOW": {
    "price": 48861.81,
    "change": -0.57
  },
  "NASDAQ": {
    "price": 24673.24,
    "change": 0.04
  },
  "TSX": {
    "price": 33318.39,
    "change": -0.79
  },
  "EUR/USD": {
    "price": 1.17,
    "change": 0.14
  },
  "GBP/USD": {
    "price": 1.3499,
    "change": 0.16
  },
  "USD/CAD": {
    "price": 1.3666,
    "change": -0.08
  },
  "USD/JPY": {
    "price": 160.026,
    "change": -0.18
  }
}