{
  "BTC": {
    "price": 76222.95,
    "change": 0.62
  },
  "ETH": {
    "price": 2255.09,
    "change": 0.12
  },
  "GOLD": {
    "price": 4636.6,
    "change": 1.65
  },
  "SILVER": {
    "price": 74.305,
    "change": 3.08
  },
  "OIL": {
    "price": 103.63,
    "change": -3.04
  },
  "S&P 500": {
    "price": 7201.3,
    "change": 0.92
  },
  "DOW": {
    "price": 49639.7,
    "change": 1.59
  },
  "NASDAQ": {
    "price": 24873.855,
    "change": 0.81
  },
  "TSX": {
    "price": 33843.59,
    "change": 1.58
  },
  "EUR/USD": {
    "price": 1.173,
    "change": 0.39
  },
  "GBP/USD": {
    "price": 1.3587,
    "change": 0.82
  },
  "USD/CAD": {
    "price": 1.3606,
    "change": -0.52
  },
  "USD/JPY": {
    "price": 156.447,
    "change": -2.41
  }
}