{
  "BTC": {
    "price": 76229.49,
    "change": 0.63
  },
  "ETH": {
    "price": 2262.0,
    "change": 0.42
  },
  "GOLD": {
    "price": 4633.3,
    "change": 1.57
  },
  "SILVER": {
    "price": 73.66,
    "change": 2.18
  },
  "OIL": {
    "price": 105.87,
    "change": -0.94
  },
  "S&P 500": {
    "price": 7161.87,
    "change": 0.36
  },
  "DOW": {
    "price": 49413.66,
    "change": 1.13
  },
  "NASDAQ": {
    "price": 24688.19,
    "change": 0.06
  },
  "TSX": {
    "price": 33687.73,
    "change": 1.11
  },
  "EUR/USD": {
    "price": 1.1727,
    "change": 0.37
  },
  "GBP/USD": {
    "price": 1.3578,
    "change": 0.75
  },
  "USD/CAD": {
    "price": 1.3614,
    "change": -0.46
  },
  "USD/JPY": {
    "price": 156.755,
    "change": -2.22
  }
}